dessiccate/__init__.py
dessiccate/_nbdev.py
dessiccate/core.py
dessiccate/pandas.py
dessiccate/plotting.py
dessiccate-0.0.13.dist-info/LICENSE
dessiccate-0.0.13.dist-info/METADATA
dessiccate-0.0.13.dist-info/WHEEL
dessiccate-0.0.13.dist-info/entry_points.txt
dessiccate-0.0.13.dist-info/top_level.txt
dessiccate-0.0.13.dist-info/RECORD
